sphinx_json_schema_spec/__init__.py
sphinx_json_schema_spec/tests/__init__.py
sphinx_json_schema_spec/tests/test_sphinx.py
sphinx_json_schema_spec-2025.1.1.dist-info/METADATA
sphinx_json_schema_spec-2025.1.1.dist-info/WHEEL
sphinx_json_schema_spec-2025.1.1.dist-info/licenses/COPYING
sphinx_json_schema_spec-2025.1.1.dist-info/RECORD
