Metadata-Version: 2.4
Name: sphinx_json_schema_spec
Version: 2025.1.1
Summary: Sphinx support for the JSON Schema specifications
Project-URL: Homepage, https://github.com/python-jsonschema/sphinx-json-schema-spec
Project-URL: Documentation, https://sphinx-json-schema-spec.readthedocs.io/
Project-URL: Issues, https://github.com/python-jsonschema/sphinx-json-schema-spec/issues/
Project-URL: Funding, https://github.com/sponsors/Julian
Project-URL: Source, https://github.com/python-jsonschema/sphinx-json-schema-spec
Author-email: Julian Berman <Julian+sphinx-json-schema-spec@GrayVines.com>
License-Expression: MIT
License-File: COPYING
Keywords: data validation,json,json schema,jsonschema,sphinx
Classifier: Development Status :: 4 - Beta
Classifier: Framework :: Sphinx :: Extension
Classifier: Intended Audience :: Developers
Classifier: Operating System :: OS Independent
Classifier: Programming Language :: Python
Classifier: Programming Language :: Python :: 3.11
Classifier: Programming Language :: Python :: 3.12
Classifier: Programming Language :: Python :: 3.13
Classifier: Programming Language :: Python :: Implementation :: CPython
Classifier: Programming Language :: Python :: Implementation :: PyPy
Classifier: Topic :: Documentation :: Sphinx
Classifier: Topic :: File Formats :: JSON :: JSON Schema
Requires-Python: >=3.11
Requires-Dist: lxml
Requires-Dist: sphinx>=5.1.1
